lincot/__init__.py
lincot/classes.py
lincot/commands.py
lincot/constants.py
lincot/functions.py
lincot-1.0.3.dist-info/LICENSE
lincot-1.0.3.dist-info/METADATA
lincot-1.0.3.dist-info/WHEEL
lincot-1.0.3.dist-info/entry_points.txt
lincot-1.0.3.dist-info/top_level.txt
lincot-1.0.3.dist-info/RECORD
