Metadata-Version: 2.1
Name: lincot
Version: 1.0.3
Summary: LINCOT: Linux GPS to TAK Gateway.
Home-page: https://github.com/snstac/lincot
Maintainer: Greg Albrecht <oss@undef.net>
Maintainer-email: oss@undef.net
License: Apache 2.0
Project-URL: CI: GitHub Actions, https://github.com/snstac/lincot/actions
Project-URL: GitHub: issues, https://github.com/snstac/lincot/issues
Project-URL: GitHub: repo, https://github.com/snstac/lincot
Keywords: Cursor on Target,CoT,ATAK,TAK,WinTAK,TAK,TAK Server
Classifier: License :: OSI Approved :: Apache Software License
Classifier: Intended Audience :: Developers
Classifier: Programming Language :: Python
Classifier: Programming Language :: Python :: 3
Classifier: Programming Language :: Python :: 3 :: Only
Classifier: Programming Language :: Python :: 3.6
Classifier: Programming Language :: Python :: 3.7
Classifier: Programming Language :: Python :: 3.8
Classifier: Programming Language :: Python :: 3.9
Classifier: Programming Language :: Python :: 3.10
Classifier: Programming Language :: Python :: 3.11
Classifier: Development Status :: 5 - Production/Stable
Classifier: Operating System :: POSIX
Classifier: Operating System :: MacOS :: MacOS X
Classifier: Operating System :: Microsoft :: Windows
Classifier: Operating System :: OS Independent
Requires-Python: <4,>=3.6
License-File: LICENSE
Requires-Dist: pytak (>=5.4.0)
Provides-Extra: test
Requires-Dist: pytest-asyncio ; extra == 'test'
Requires-Dist: pytest-cov ; extra == 'test'
Requires-Dist: pylint ; extra == 'test'
Requires-Dist: flake8 ; extra == 'test'
Requires-Dist: black ; extra == 'test'
Requires-Dist: cryptography ; extra == 'test'
Provides-Extra: with_takproto
Requires-Dist: takproto (>=2.0.0) ; extra == 'with_takproto'
